flamapy/metamodels/z3_metamodel/__init__.py
flamapy/metamodels/z3_metamodel/models/__init__.py
flamapy/metamodels/z3_metamodel/models/z3_model.py
flamapy/metamodels/z3_metamodel/operations/__init__.py
flamapy/metamodels/z3_metamodel/operations/z3_attribute_optimization.py
flamapy/metamodels/z3_metamodel/operations/z3_configurations.py
flamapy/metamodels/z3_metamodel/operations/z3_configurations_number.py
flamapy/metamodels/z3_metamodel/operations/z3_core_features.py
flamapy/metamodels/z3_metamodel/operations/z3_dead_features.py
flamapy/metamodels/z3_metamodel/operations/z3_false_optional_features.py
flamapy/metamodels/z3_metamodel/operations/z3_satisfiable.py
flamapy/metamodels/z3_metamodel/operations/z3_satisfiable_configuration.py
flamapy/metamodels/z3_metamodel/operations/interfaces/__init__.py
flamapy/metamodels/z3_metamodel/operations/interfaces/attribute_optimization.py
flamapy/metamodels/z3_metamodel/transformations/__init__.py
flamapy/metamodels/z3_metamodel/transformations/fm_to_z3.py
flamapy_z3-2.1.0.dev1.dist-info/METADATA
flamapy_z3-2.1.0.dev1.dist-info/WHEEL
flamapy_z3-2.1.0.dev1.dist-info/top_level.txt
flamapy_z3-2.1.0.dev1.dist-info/RECORD
