Metadata-Version: 2.4
Name: flamapy-z3
Version: 2.1.0.dev1
Summary: z3-plugin for the automated analysis of feature models
Home-page: https://github.com/flamapy/z3_metamodel
Author: Flamapy
Author-email: flamapy@us.es
Classifier: Programming Language :: Python :: 3
Classifier: License :: OSI Approved :: GNU General Public License v3 or later (GPLv3+)
Classifier: Operating System :: OS Independent
Requires-Python: >=3.9
Requires-Dist: flamapy-fw~=2.1.0.dev1
Requires-Dist: flamapy-fm~=2.1.0.dev1
Requires-Dist: z3-solver~=4.14.1.0
Provides-Extra: dev
Requires-Dist: pytest; extra == "dev"
Requires-Dist: pytest-mock; extra == "dev"
Requires-Dist: prospector; extra == "dev"
Requires-Dist: mypy; extra == "dev"
Requires-Dist: coverage; extra == "dev"
Dynamic: author
Dynamic: author-email
Dynamic: classifier
Dynamic: description
Dynamic: description-content-type
Dynamic: home-page
Dynamic: provides-extra
Dynamic: requires-dist
Dynamic: requires-python
Dynamic: summary
